pyhowto/__init__.py
pyhowto/__main__.py
pyhowto/providers.py
pyhowto-0.0.2.dist-info/LICENSE
pyhowto-0.0.2.dist-info/METADATA
pyhowto-0.0.2.dist-info/WHEEL
pyhowto-0.0.2.dist-info/entry_points.txt
pyhowto-0.0.2.dist-info/RECORD
