Metadata-Version: 2.1
Name: pyhowto
Version: 0.0.2
Summary: Ask AI how to do something
Home-page: https://github.com/ablil/pyhowto
Author: ablil
Author-email: ablil@proton.me
Maintainer: ablil
Maintainer-email: ablil@proton.me
Requires-Python: >=3.12,<4.0
Classifier: Programming Language :: Python :: 3
Classifier: Programming Language :: Python :: 3.12
Classifier: Programming Language :: Python :: 3.13
Requires-Dist: google-generativeai (>=0.8.4,<0.9.0)
Requires-Dist: openai (>=1.73.0,<2.0.0)
Requires-Dist: requests (>=2.32.3,<3.0.0)
Project-URL: Bug Tracker, https://github.com/ablil/pyhowto/issues
Project-URL: Repository, https://github.com/ablil/pyhowto
